test_print_name/__init__.py
test_print_name/test_songzijie.py
test_print_name-0.0.1.dist-info/METADATA
test_print_name-0.0.1.dist-info/WHEEL
test_print_name-0.0.1.dist-info/top_level.txt
test_print_name-0.0.1.dist-info/RECORD
