Metadata-Version: 2.1
Name: test-print-name
Version: 0.0.1
Summary: songzijie study PyPI
Author: songzijie
Author-email: 1171322827@qq.com
Classifier: Programming Language :: Python :: 3
Classifier: License :: OSI Approved :: MIT License
Classifier: Operating System :: OS Independent
Requires-Python: >=3
